.gitignore
.travis.yml
CHANGES.rst
LICENSE.rst
README.rst
VERSION.txt
ez_setup.py
requirements.txt
setup.cfg
setup.py
tox.ini
cheshire3/__init__.py
cheshire3/baseObjects.py
cheshire3/baseStore.py
cheshire3/bootstrap.py
cheshire3/configParser.py
cheshire3/cqlParser.py
cheshire3/database.py
cheshire3/document.py
cheshire3/documentFactory.py
cheshire3/documentStore.py
cheshire3/dynamic.py
cheshire3/exceptions.py
cheshire3/extractor.py
cheshire3/index.py
cheshire3/indexStore.py
cheshire3/internal.py
cheshire3/licensing.py
cheshire3/logger.py
cheshire3/marc_to_unicode.py
cheshire3/marc_utils.py
cheshire3/normalizer.py
cheshire3/objectStore.py
cheshire3/parser.py
cheshire3/permissionHandler.py
cheshire3/preParser.py
cheshire3/protocolMap.py
cheshire3/queryFactory.py
cheshire3/queryStore.py
cheshire3/record.py
cheshire3/recordStore.py
cheshire3/resultSet.py
cheshire3/resultSetStore.py
cheshire3/selector.py
cheshire3/server.py
cheshire3/session.py
cheshire3/tokenMerger.py
cheshire3/tokenizer.py
cheshire3/transformer.py
cheshire3/user.py
cheshire3/utils.py
cheshire3/workflow.py
cheshire3/xpathProcessor.py
cheshire3.egg-info/PKG-INFO
cheshire3.egg-info/SOURCES.txt
cheshire3.egg-info/dependency_links.txt
cheshire3.egg-info/entry_points.txt
cheshire3.egg-info/requires.txt
cheshire3.egg-info/top_level.txt
cheshire3/commands/__init__.py
cheshire3/commands/cmd_utils.py
cheshire3/commands/console.py
cheshire3/commands/init.py
cheshire3/commands/load.py
cheshire3/commands/register.py
cheshire3/commands/search.py
cheshire3/commands/serve.py
cheshire3/commands/unregister.py
cheshire3/configs/authStore.xml
cheshire3/configs/basicConfigs.xml
cheshire3/configs/configStore.xml
cheshire3/configs/serverConfig.xml
cheshire3/configs/workflow.xml
cheshire3/configs/zserver.xml
cheshire3/configs/databases/.gitignore
cheshire3/configs/databases/README.mdown
cheshire3/configs/datamining/preParser.xml
cheshire3/configs/formats/preParser.xml
cheshire3/configs/formats/workflow.xml
cheshire3/configs/graph/extractor.xml
cheshire3/configs/graph/parser.xml
cheshire3/configs/graph/transformer.xml
cheshire3/configs/textmining/documentFactory.xml
cheshire3/configs/textmining/extractor.xml
