Metadata-Version: 1.1
Name: cheshire3
Version: 1.1.6
Summary: Cheshire3 Search and Retrieval Engine and Information Framework
Home-page: http://cheshire3.liv.ac.uk /
Author: John Harrison
Author-email: john.harrison@liv.ac.uk
License: BSD
Download-URL: http://cheshire3.liv.ac.uk/download/1.1/src/cheshire3-1.1.6.tar.gz
Keywords: xml document search information retrieval engine data text
Platform: UNKNOWN
Classifier: Intended Audience :: Developers
Classifier: Intended Audience :: Information Technology
Classifier: License :: OSI Approved :: BSD License
Classifier: Programming Language :: Python :: 2.6
Classifier: Programming Language :: Python :: 2.7
Classifier: Topic :: Internet :: WWW/HTTP :: Indexing/Search
Classifier: Topic :: Internet :: WWW/HTTP :: WSGI :: Application
Classifier: Topic :: Internet :: Z39.50
Classifier: Topic :: Text Processing :: Indexing
Classifier: Topic :: Text Processing :: Linguistic
Classifier: Topic :: Text Processing :: Markup
Requires: lxml(>=2.1)
Requires: bsddb
Requires: dateutil
Requires: argparse
